mcp_mermaid/__init__.py
mcp_mermaid/_version.py
mcp_mermaid/server.py
mcp_mermaid/core/__init__.py
mcp_mermaid/core/generator.py
mcp_mermaid/core/logger.py
mcp_mermaid/core/optimizer.py
mcp_mermaid/core/uploader.py
mcp_mermaid/themes/__init__.py
mcp_mermaid/themes/configs.py
mcp_mermaid/tools/__init__.py
mcp_mermaid/tools/mermaid_tools.py
mcp_mermaid-1.0.0.dist-info/METADATA
mcp_mermaid-1.0.0.dist-info/WHEEL
mcp_mermaid-1.0.0.dist-info/entry_points.txt
mcp_mermaid-1.0.0.dist-info/top_level.txt
mcp_mermaid-1.0.0.dist-info/RECORD
