Metadata-Version: 2.4
Name: mcp-mermaid
Version: 1.0.0
Summary: 智能Mermaid图表生成工具，支持布局优化、主题系统和高质量输出的MCP服务器
Home-page: https://github.com/mcp-mermaid/mcp-mermaid
Author: MCP-Mermaid Team
Author-email: MCP-Mermaid Team <dev@mcp-mermaid.com>
Maintainer-email: MCP-Mermaid Team <dev@mcp-mermaid.com>
License: MIT
Project-URL: Homepage, https://github.com/mcp-mermaid/mcp-mermaid
Project-URL: Documentation, https://github.com/mcp-mermaid/mcp-mermaid/blob/main/README.md
Project-URL: Repository, https://github.com/mcp-mermaid/mcp-mermaid.git
Project-URL: Bug Reports, https://github.com/mcp-mermaid/mcp-mermaid/issues
Project-URL: Changelog, https://github.com/mcp-mermaid/mcp-mermaid/blob/main/CHANGELOG.md
Keywords: mcp,mermaid,diagram,visualization,charts,model-context-protocol
Classifier: Development Status :: 5 - Production/Stable
Classifier: Intended Audience :: Developers
Classifier: Operating System :: OS Independent
Classifier: Programming Language :: Python :: 3
Classifier: Programming Language :: Python :: 3.8
Classifier: Programming Language :: Python :: 3.9
Classifier: Programming Language :: Python :: 3.10
Classifier: Programming Language :: Python :: 3.11
Classifier: Programming Language :: Python :: 3.12
Classifier: Topic :: Software Development :: Libraries :: Python Modules
Classifier: Topic :: Scientific/Engineering :: Visualization
Classifier: Topic :: Text Processing :: Markup
Requires-Python: >=3.8
Requires-Dist: requests>=2.25.0
Provides-Extra: dev
Requires-Dist: pytest>=6.0; extra == "dev"
Requires-Dist: pytest-asyncio>=0.18.0; extra == "dev"
Requires-Dist: black>=21.0; extra == "dev"
Requires-Dist: flake8>=3.8.0; extra == "dev"
Requires-Dist: mypy>=0.800; extra == "dev"
Requires-Dist: types-requests>=2.25.0; extra == "dev"
Requires-Dist: build>=0.8.0; extra == "dev"
Requires-Dist: twine>=4.0.0; extra == "dev"
Provides-Extra: test
Requires-Dist: pytest>=6.0; extra == "test"
Requires-Dist: pytest-asyncio>=0.18.0; extra == "test"
Requires-Dist: pytest-cov>=2.0; extra == "test"
Provides-Extra: docker
Requires-Dist: gunicorn>=20.0.0; extra == "docker"
Dynamic: author
Dynamic: home-page
Dynamic: requires-python
